MANIFEST.in
setup.py
src/dowser/__init__.py
src/dowser/__version__.py
src/dowser/graphs.html
src/dowser/main.css
src/dowser/reftree.py
src/dowser/trace.html
src/dowser/tree.html
src/dowser.egg-info/PKG-INFO
src/dowser.egg-info/SOURCES.txt
src/dowser.egg-info/dependency_links.txt
src/dowser.egg-info/entry_points.txt
src/dowser.egg-info/namespace_packages.txt
src/dowser.egg-info/not-zip-safe
src/dowser.egg-info/requires.txt
src/dowser.egg-info/top_level.txt