Metadata-Version: 1.1
Name: dowser
Version: 0.1
Summary: Debugging Python’s Memory Usage with Dowser
Home-page: https://github.com/Infinidat/dowser
Author: Guy Rozendorn
Author-email: guy@rzn.co.il
License: PSF
Platform: UNKNOWN
Classifier: Intended Audience :: Developers
Classifier: Intended Audience :: System Administrators
Classifier: License :: OSI Approved :: Python Software Foundation License
Classifier: Operating System :: OS Independent
Classifier: Programming Language :: Python
Classifier: Topic :: Software Development :: Libraries :: Python Modules
